word_mover_distance/__init__.py
word_mover_distance/model.py
word_mover_distance-0.0.2.dist-info/LICENSE
word_mover_distance-0.0.2.dist-info/METADATA
word_mover_distance-0.0.2.dist-info/WHEEL
word_mover_distance-0.0.2.dist-info/top_level.txt
word_mover_distance-0.0.2.dist-info/RECORD
