Metadata-Version: 2.1
Name: word-mover-distance
Version: 0.0.2
Summary: Compute Word Mover's Distance using any type of Word Embedding model
Home-page: https://github.com/hechmik/word_mover_distance
Author: Khaled Hechmi
Author-email: hechmi.khaled1995@gmail.com
License: UNKNOWN
Keywords: nlp wordembeddings wordmoverdistance similarity
Platform: UNKNOWN
Classifier: Programming Language :: Python :: 3
Classifier: License :: OSI Approved :: MIT License
Classifier: Operating System :: OS Independent
Requires-Python: >=3.6
Requires-Dist: numpy
Requires-Dist: gensim
Requires-Dist: pyemd
